{"openapi":"3.1.0","info":{"title":"OpenAPI definition","version":"v0"},"servers":[{"url":"http://127.0.0.1:8080","description":"Generated server url"}],"paths":{"/api/admin/source-principals/{principalId}/mapping":{"put":{"tags":["admin-source-access-controller"],"summary":"Confirm a principal maps to an internal user","operationId":"confirmAdminSourceMapping","parameters":[{"name":"principalId","in":"path","required":true,"schema":{"type":"string","format":"uuid"}}],"requestBody":{"content":{"application/json":{"schema":{"$ref":"#/components/schemas/ConfirmMappingRequest"}}},"required":true},"responses":{"200":{"description":"OK","content":{"*/*":{"schema":{"$ref":"#/components/schemas/AdminSourcePrincipalResponse"}}}}}},"delete":{"tags":["admin-source-access-controller"],"summary":"Revoke a principal's active mapping","operationId":"revokeAdminSourceMapping","parameters":[{"name":"principalId","in":"path","required":true,"schema":{"type":"string","format":"uuid"}}],"responses":{"200":{"description":"OK","content":{"*/*":{"schema":{"$ref":"#/components/schemas/AdminSourcePrincipalResponse"}}}}}}},"/api/admin/source-connections/identity-trust":{"put":{"tags":["admin-source-access-controller"],"summary":"Record the identity trust for a connection","operationId":"setAdminSourceConnectionTrust","requestBody":{"content":{"application/json":{"schema":{"$ref":"#/components/schemas/IdentityTrustRequest"}}},"required":true},"responses":{"200":{"description":"OK","content":{"*/*":{"schema":{"$ref":"#/components/schemas/AdminSourceConnectionResponse"}}}}}}},"/api/admin/connectors/{sourceSystem}/{connectionKey}":{"put":{"tags":["admin-connector-controller"],"summary":"Record how a connection is crawled","operationId":"configureAdminConnection","parameters":[{"name":"sourceSystem","in":"path","required":true,"schema":{"type":"string"}},{"name":"connectionKey","in":"path","required":true,"schema":{"type":"string"}}],"requestBody":{"content":{"application/json":{"schema":{"$ref":"#/components/schemas/ConfigureConnectionRequest"}}},"required":true},"responses":{"200":{"description":"OK","content":{"*/*":{"schema":{"$ref":"#/components/schemas/AdminConnectionResponse"}}}}}}},"/api/admin/connectors/{sourceSystem}/{connectionKey}/credential":{"put":{"tags":["admin-connector-controller"],"summary":"Store a credential for a connection","operationId":"setAdminConnectionCredential","parameters":[{"name":"sourceSystem","in":"path","required":true,"schema":{"type":"string"}},{"name":"connectionKey","in":"path","required":true,"schema":{"type":"string"}}],"requestBody":{"content":{"application/json":{"schema":{"$ref":"#/components/schemas/ConnectorCredentialRequest"}}},"required":true},"responses":{"204":{"description":"No Content"}}},"delete":{"tags":["admin-connector-controller"],"summary":"Forget a connection's stored credential","operationId":"forgetAdminConnectionCredential","parameters":[{"name":"sourceSystem","in":"path","required":true,"schema":{"type":"string"}},{"name":"connectionKey","in":"path","required":true,"schema":{"type":"string"}}],"responses":{"204":{"description":"No Content"}}}},"/api/sources":{"get":{"tags":["source-controller"],"summary":"List sources visible to the current user","operationId":"listSources","responses":{"200":{"description":"OK","content":{"*/*":{"schema":{"type":"array","items":{"$ref":"#/components/schemas/SourceResponse"}}}}}}},"post":{"tags":["source-controller"],"summary":"Upload a source for asynchronous ingestion","operationId":"uploadSource","parameters":[{"name":"classification","in":"query","required":false,"schema":{"type":"string","default":"CONFIDENTIAL","enum":["PUBLIC","INTERNAL","CONFIDENTIAL","RESTRICTED"]}},{"name":"knowledgeSpaceId","in":"query","required":true,"schema":{"type":"string","format":"uuid"}}],"requestBody":{"content":{"multipart/form-data":{"schema":{"type":"object","properties":{"file":{"type":"string","format":"binary"}},"required":["file"]}}}},"responses":{"201":{"description":"Created","content":{"*/*":{"schema":{"$ref":"#/components/schemas/SourceResponse"}}}}}}},"/api/assistant/chat":{"post":{"tags":["assistant-controller"],"summary":"Stream an answer from permission-verified knowledge","operationId":"streamAssistantChat","requestBody":{"content":{"application/json":{"schema":{"$ref":"#/components/schemas/AssistantChatRequest"}}},"required":true},"responses":{"200":{"description":"OK","content":{"text/event-stream":{"schema":{"type":"array","items":{"$ref":"#/components/schemas/ServerSentEventString"}}}}}}}},"/api/assets":{"get":{"tags":["capability-asset-controller"],"operationId":"search","parameters":[{"name":"status","in":"query","required":false,"schema":{"type":"string","enum":["DRAFT","IN_REVIEW","APPROVED","REJECTED","DEPRECATED"]}},{"name":"assetType","in":"query","required":false,"schema":{"type":"string","enum":["PROMPT_TEMPLATE","WORKFLOW_AUTOMATION","AI_AGENT","KNOWLEDGE_BOT","ANALYTICS_BRIEF","CONTENT_GENERATOR","DATA_EXTRACTION","EVALUATION_CHECKLIST","PLAYBOOK","HANDOVER_PACK","GOVERNANCE_GUARDRAIL","COPILOT"]}},{"name":"q","in":"query","required":false,"schema":{"type":"string"}}],"responses":{"200":{"description":"OK","content":{"*/*":{"schema":{"type":"array","items":{"$ref":"#/components/schemas/CapabilityAssetResponse"}}}}}}},"post":{"tags":["capability-asset-controller"],"operationId":"create","requestBody":{"content":{"application/json":{"schema":{"$ref":"#/components/schemas/CreateAssetRequest"}}},"required":true},"responses":{"200":{"description":"OK","content":{"*/*":{"schema":{"$ref":"#/components/schemas/CapabilityAssetResponse"}}}}}}},"/api/assets/{assetId}/usage":{"post":{"tags":["capability-asset-controller"],"operationId":"recordUsage","parameters":[{"name":"assetId","in":"path","required":true,"schema":{"type":"string","format":"uuid"}}],"requestBody":{"content":{"application/json":{"schema":{"$ref":"#/components/schemas/UsageRequest"}}},"required":true},"responses":{"200":{"description":"OK","content":{"*/*":{"schema":{"$ref":"#/components/schemas/UsageResponse"}}}}}}},"/api/admin/connectors/{sourceSystem}/{connectionKey}/test":{"post":{"tags":["admin-connector-controller"],"summary":"Check a connection's stored credential","operationId":"testAdminConnection","parameters":[{"name":"sourceSystem","in":"path","required":true,"schema":{"type":"string"}},{"name":"connectionKey","in":"path","required":true,"schema":{"type":"string"}}],"responses":{"200":{"description":"OK","content":{"*/*":{"schema":{"$ref":"#/components/schemas/AdminConnectorProbeResponse"}}}}}}},"/api/admin/connectors/{sourceSystem}/test":{"post":{"tags":["admin-connector-controller"],"summary":"Check a credential without storing it","operationId":"testAdminConnectorCredential","parameters":[{"name":"sourceSystem","in":"path","required":true,"schema":{"type":"string"}}],"requestBody":{"content":{"application/json":{"schema":{"$ref":"#/components/schemas/ConnectorCredentialRequest"}}},"required":true},"responses":{"200":{"description":"OK","content":{"*/*":{"schema":{"$ref":"#/components/schemas/AdminConnectorProbeResponse"}}}}}}},"/api/assets/{assetId}/submit-review":{"patch":{"tags":["capability-asset-controller"],"operationId":"submitForReview","parameters":[{"name":"assetId","in":"path","required":true,"schema":{"type":"string","format":"uuid"}}],"requestBody":{"content":{"application/json":{"schema":{"$ref":"#/components/schemas/ReviewRequest"}}}},"responses":{"200":{"description":"OK","content":{"*/*":{"schema":{"$ref":"#/components/schemas/CapabilityAssetResponse"}}}}}}},"/api/assets/{assetId}/reject":{"patch":{"tags":["capability-asset-controller"],"operationId":"reject","parameters":[{"name":"assetId","in":"path","required":true,"schema":{"type":"string","format":"uuid"}}],"requestBody":{"content":{"application/json":{"schema":{"$ref":"#/components/schemas/ReviewRequest"}}}},"responses":{"200":{"description":"OK","content":{"*/*":{"schema":{"$ref":"#/components/schemas/CapabilityAssetResponse"}}}}}}},"/api/assets/{assetId}/deprecate":{"patch":{"tags":["capability-asset-controller"],"operationId":"deprecate","parameters":[{"name":"assetId","in":"path","required":true,"schema":{"type":"string","format":"uuid"}}],"requestBody":{"content":{"application/json":{"schema":{"$ref":"#/components/schemas/ReviewRequest"}}}},"responses":{"200":{"description":"OK","content":{"*/*":{"schema":{"$ref":"#/components/schemas/CapabilityAssetResponse"}}}}}}},"/api/assets/{assetId}/backup-owner":{"patch":{"tags":["capability-asset-controller"],"operationId":"assignBackupOwner","parameters":[{"name":"assetId","in":"path","required":true,"schema":{"type":"string","format":"uuid"}}],"requestBody":{"content":{"application/json":{"schema":{"$ref":"#/components/schemas/BackupOwnerRequest"}}},"required":true},"responses":{"200":{"description":"OK","content":{"*/*":{"schema":{"$ref":"#/components/schemas/CapabilityAssetResponse"}}}}}}},"/api/assets/{assetId}/approve":{"patch":{"tags":["capability-asset-controller"],"operationId":"approve","parameters":[{"name":"assetId","in":"path","required":true,"schema":{"type":"string","format":"uuid"}}],"requestBody":{"content":{"application/json":{"schema":{"$ref":"#/components/schemas/ReviewRequest"}}}},"responses":{"200":{"description":"OK","content":{"*/*":{"schema":{"$ref":"#/components/schemas/CapabilityAssetResponse"}}}}}}},"/api/admin/users/{userId}":{"patch":{"tags":["admin-user-controller"],"summary":"Change a user's role or activation","operationId":"updateAdminUser","parameters":[{"name":"userId","in":"path","required":true,"schema":{"type":"string","format":"uuid"}}],"requestBody":{"content":{"application/json":{"schema":{"$ref":"#/components/schemas/UpdateAdminUserRequest"}}},"required":true},"responses":{"200":{"description":"OK","content":{"*/*":{"schema":{"$ref":"#/components/schemas/AdminUserResponse"}}}}}}},"/api/session":{"get":{"tags":["browser-session-controller"],"summary":"Read the current browser session","operationId":"getBrowserSession","responses":{"200":{"description":"OK","content":{"*/*":{"schema":{"$ref":"#/components/schemas/SessionResponse"}}}}}}},"/api/session/csrf":{"get":{"tags":["browser-session-controller"],"summary":"Issue a CSRF token for browser mutations","operationId":"getBrowserCsrfToken","responses":{"200":{"description":"OK","content":{"*/*":{"schema":{"$ref":"#/components/schemas/CsrfResponse"}}}}}}},"/api/organization/context":{"get":{"tags":["organization-context-controller"],"operationId":"context","responses":{"200":{"description":"OK","content":{"*/*":{"schema":{"$ref":"#/components/schemas/OrganizationContextResponse"}}}}}}},"/api/me":{"get":{"tags":["me-controller"],"operationId":"me","responses":{"200":{"description":"OK","content":{"*/*":{"schema":{"$ref":"#/components/schemas/MeResponse"}}}}}}},"/api/knowledge/search":{"get":{"tags":["knowledge-search-controller"],"summary":"Search permission-verified knowledge evidence","operationId":"searchKnowledge","parameters":[{"name":"q","in":"query","required":true,"schema":{"type":"string"}},{"name":"limit","in":"query","required":false,"schema":{"type":"integer","format":"int32"}}],"responses":{"200":{"description":"OK","content":{"*/*":{"schema":{"$ref":"#/components/schemas/KnowledgeSearchResponse"}}}}}}},"/api/knowledge-spaces/upload-targets":{"get":{"tags":["knowledge-space-controller"],"summary":"List Knowledge Spaces where the current user may add knowledge","operationId":"listKnowledgeSpaceUploadTargets","responses":{"200":{"description":"OK","content":{"*/*":{"schema":{"type":"array","items":{"$ref":"#/components/schemas/KnowledgeSpaceResponse"}}}}}}}},"/api/health":{"get":{"tags":["health-controller"],"operationId":"health","responses":{"200":{"description":"OK","content":{"*/*":{"schema":{"type":"object","additionalProperties":{"type":"string"}}}}}}}},"/api/assets/{assetId}":{"get":{"tags":["capability-asset-controller"],"operationId":"get","parameters":[{"name":"assetId","in":"path","required":true,"schema":{"type":"string","format":"uuid"}}],"responses":{"200":{"description":"OK","content":{"*/*":{"schema":{"$ref":"#/components/schemas/CapabilityAssetResponse"}}}}}}},"/api/assets/{assetId}/versions":{"get":{"tags":["capability-asset-controller"],"operationId":"versions","parameters":[{"name":"assetId","in":"path","required":true,"schema":{"type":"string","format":"uuid"}}],"responses":{"200":{"description":"OK","content":{"*/*":{"schema":{"type":"array","items":{"$ref":"#/components/schemas/AssetVersionResponse"}}}}}}}},"/api/admin/users":{"get":{"tags":["admin-user-controller"],"summary":"List internal users with their sign-in and mapping status","operationId":"listAdminUsers","responses":{"200":{"description":"OK","content":{"*/*":{"schema":{"type":"array","items":{"$ref":"#/components/schemas/AdminUserResponse"}}}}}}}},"/api/admin/source-principals":{"get":{"tags":["admin-source-access-controller"],"summary":"List observed principals and their mapping","operationId":"listAdminSourcePrincipals","responses":{"200":{"description":"OK","content":{"*/*":{"schema":{"type":"array","items":{"$ref":"#/components/schemas/AdminSourcePrincipalResponse"}}}}}}}},"/api/admin/source-groups":{"get":{"tags":["admin-source-access-controller"],"summary":"List source groups with their sealed membership","operationId":"listAdminSourceGroups","responses":{"200":{"description":"OK","content":{"*/*":{"schema":{"type":"array","items":{"$ref":"#/components/schemas/AdminSourceGroupResponse"}}}}}}}},"/api/admin/source-connections":{"get":{"tags":["admin-source-access-controller"],"summary":"List observed connections and their trust level","operationId":"listAdminSourceConnections","responses":{"200":{"description":"OK","content":{"*/*":{"schema":{"type":"array","items":{"$ref":"#/components/schemas/AdminSourceConnectionResponse"}}}}}}}},"/api/admin/connectors/{sourceSystem}":{"get":{"tags":["admin-connector-controller"],"summary":"List a source's connections and their crawl settings","operationId":"listAdminConnections","parameters":[{"name":"sourceSystem","in":"path","required":true,"schema":{"type":"string"}}],"responses":{"200":{"description":"OK","content":{"*/*":{"schema":{"type":"array","items":{"$ref":"#/components/schemas/AdminConnectionResponse"}}}}}}}},"/api/admin/connectors/{sourceSystem}/{connectionKey}/activity":{"get":{"tags":["admin-connector-controller"],"summary":"Read what a connection has crawled and what went wrong","operationId":"getAdminConnectionActivity","parameters":[{"name":"sourceSystem","in":"path","required":true,"schema":{"type":"string"}},{"name":"connectionKey","in":"path","required":true,"schema":{"type":"string"}}],"responses":{"200":{"description":"OK","content":{"*/*":{"schema":{"$ref":"#/components/schemas/AdminConnectionActivityResponse"}}}}}}},"/api/admin/connectors/sources":{"get":{"tags":["admin-connector-controller"],"summary":"List the sources this deployment can ingest","operationId":"listAdminConnectorSources","responses":{"200":{"description":"OK","content":{"*/*":{"schema":{"type":"array","items":{"$ref":"#/components/schemas/AdminConnectorSourceResponse"}}}}}}}}},"components":{"schemas":{"ConfirmMappingRequest":{"type":"object","properties":{"appUserId":{"type":"string","format":"uuid"}}},"AdminSourceMappingResponse":{"type":"object","properties":{"id":{"type":"string","format":"uuid"},"appUserId":{"type":"string","format":"uuid"},"appUserName":{"type":"string"},"appUserEmail":{"type":"string"},"method":{"type":"string","enum":["IDP_JOIN","SSO_EMAIL_JOIN","SELF_CLAIM","ADMIN_CONFIRMED"]},"status":{"type":"string","enum":["ACTIVE","REVOKED"]},"evidence":{"type":"string"},"verifiedAt":{"type":"string","format":"date-time"}}},"AdminSourcePrincipalResponse":{"type":"object","properties":{"id":{"type":"string","format":"uuid"},"sourceSystem":{"type":"string"},"sourceConnectionKey":{"type":"string"},"externalKey":{"type":"string"},"kind":{"type":"string","enum":["SOURCE_USER","SOURCE_GROUP"]},"observedEmail":{"type":"string"},"observedDisplayName":{"type":"string"},"ssoVerified":{"type":"boolean"},"lastSeenAt":{"type":"string","format":"date-time"},"mapping":{"$ref":"#/components/schemas/AdminSourceMappingResponse"}}},"IdentityTrustRequest":{"type":"object","properties":{"sourceSystem":{"type":"string"},"sourceConnectionKey":{"type":"string"},"identityTrust":{"type":"string","enum":["UNTRUSTED","SSO_VERIFIED"]}}},"AdminSourceConnectionResponse":{"type":"object","properties":{"sourceSystem":{"type":"string"},"sourceConnectionKey":{"type":"string"},"identityTrust":{"type":"string","enum":["UNTRUSTED","SSO_VERIFIED"]},"trustDecidedByUserId":{"type":"string","format":"uuid"},"trustDecidedAt":{"type":"string","format":"date-time"},"userCount":{"type":"integer","format":"int32"},"mappedUserCount":{"type":"integer","format":"int32"},"unmappedUserCount":{"type":"integer","format":"int32"},"groupCount":{"type":"integer","format":"int32"},"lastSeenAt":{"type":"string","format":"date-time"}}},"ConfigureConnectionRequest":{"type":"object","properties":{"crawlEnabled":{"type":"boolean"},"knowledgeSpaceId":{"type":"string","format":"uuid"},"actorUserId":{"type":"string","format":"uuid"},"sourceConfig":{"type":"object","additionalProperties":{}},"contentCrawlIntervalSeconds":{"type":"integer","format":"int64"}}},"AdminConnectionResponse":{"type":"object","properties":{"sourceSystem":{"type":"string"},"sourceConnectionKey":{"type":"string"},"identityTrust":{"type":"string","enum":["UNTRUSTED","SSO_VERIFIED"]},"crawlEnabled":{"type":"boolean"},"knowledgeSpaceId":{"type":"string","format":"uuid"},"actorUserId":{"type":"string","format":"uuid"},"sourceConfig":{"type":"object","additionalProperties":{}},"contentCrawlIntervalSeconds":{"type":"integer","format":"int64"},"credentialSet":{"type":"boolean"},"credentialSetByUserId":{"type":"string","format":"uuid"},"credentialSetAt":{"type":"string","format":"date-time"},"configuredByUserId":{"type":"string","format":"uuid"},"configuredAt":{"type":"string","format":"date-time"}}},"ConnectorCredentialRequest":{"type":"object","properties":{"credential":{"type":"string"}}},"SourceResponse":{"type":"object","properties":{"id":{"type":"string","format":"uuid"},"title":{"type":"string"},"sourceSystem":{"type":"string"},"aclAuthority":{"type":"string"},"status":{"type":"string"},"classification":{"type":"string"},"fileName":{"type":"string"},"mediaType":{"type":"string"},"contentLength":{"type":"integer","format":"int64"},"failureCode":{"type":"string"},"failureMessage":{"type":"string"},"embeddingProfileKey":{"type":"string"},"embeddingProvider":{"type":"string"},"embeddingModel":{"type":"string"},"embeddingDimensions":{"type":"integer","format":"int32"},"createdAt":{"type":"string","format":"date-time"},"updatedAt":{"type":"string","format":"date-time"}}},"AssistantChatRequest":{"type":"object","properties":{"message":{"type":"string","maxLength":4000,"minLength":0},"limit":{"type":"integer","format":"int32"}},"required":["message"]},"ServerSentEventString":{},"CreateAssetRequest":{"type":"object","properties":{"organizationId":{"type":"string","format":"uuid"},"departmentId":{"type":"string","format":"uuid"},"title":{"type":"string","minLength":1},"summary":{"type":"string","minLength":1},"assetType":{"type":"string","enum":["PROMPT_TEMPLATE","WORKFLOW_AUTOMATION","AI_AGENT","KNOWLEDGE_BOT","ANALYTICS_BRIEF","CONTENT_GENERATOR","DATA_EXTRACTION","EVALUATION_CHECKLIST","PLAYBOOK","HANDOVER_PACK","GOVERNANCE_GUARDRAIL","COPILOT"]},"useCase":{"type":"string"},"businessProcess":{"type":"string"},"aiTool":{"type":"string"},"tagNames":{"type":"string"},"ownerUserId":{"type":"string","format":"uuid"},"backupOwnerUserId":{"type":"string","format":"uuid"},"createdByUserId":{"type":"string","format":"uuid"},"visibility":{"type":"string","enum":["PRIVATE","TEAM","ORGANIZATION"]},"riskLevel":{"type":"string","enum":["LOW","MEDIUM","HIGH"]},"promptTemplate":{"type":"string"},"workflowStepsJson":{"type":"string"},"inputSchemaJson":{"type":"string"},"outputSchemaJson":{"type":"string"},"exampleInput":{"type":"string"},"exampleOutput":{"type":"string"}},"required":["summary","title"]},"CapabilityAssetResponse":{"type":"object","properties":{"id":{"type":"string","format":"uuid"},"organizationId":{"type":"string","format":"uuid"},"departmentId":{"type":"string","format":"uuid"},"title":{"type":"string"},"summary":{"type":"string"},"assetType":{"type":"string","enum":["PROMPT_TEMPLATE","WORKFLOW_AUTOMATION","AI_AGENT","KNOWLEDGE_BOT","ANALYTICS_BRIEF","CONTENT_GENERATOR","DATA_EXTRACTION","EVALUATION_CHECKLIST","PLAYBOOK","HANDOVER_PACK","GOVERNANCE_GUARDRAIL","COPILOT"]},"useCase":{"type":"string"},"businessProcess":{"type":"string"},"aiTool":{"type":"string"},"tagNames":{"type":"string"},"ownerUserId":{"type":"string","format":"uuid"},"backupOwnerUserId":{"type":"string","format":"uuid"},"status":{"type":"string","enum":["DRAFT","IN_REVIEW","APPROVED","REJECTED","DEPRECATED"]},"visibility":{"type":"string","enum":["PRIVATE","TEAM","ORGANIZATION"]},"riskLevel":{"type":"string","enum":["LOW","MEDIUM","HIGH"]},"currentVersionId":{"type":"string","format":"uuid"},"createdByUserId":{"type":"string","format":"uuid"},"usageCount":{"type":"integer","format":"int64"},"createdAt":{"type":"string","format":"date-time"},"updatedAt":{"type":"string","format":"date-time"}}},"UsageRequest":{"type":"object","properties":{"userId":{"type":"string","format":"uuid"},"eventType":{"type":"string","enum":["VIEWED","COPIED","USED","SHARED"]},"metadataJson":{"type":"string"}},"required":["eventType"]},"UsageResponse":{"type":"object","properties":{"assetId":{"type":"string","format":"uuid"},"usageCount":{"type":"integer","format":"int64"}}},"AdminConnectorProbeResponse":{"type":"object","properties":{"authenticated":{"type":"boolean"},"connectionKey":{"type":"string"},"accountName":{"type":"string"},"identityName":{"type":"string"},"canReadContent":{"type":"boolean"},"errorCode":{"type":"string"}}},"ReviewRequest":{"type":"object","properties":{"reviewerUserId":{"type":"string","format":"uuid"},"comment":{"type":"string"}}},"BackupOwnerRequest":{"type":"object","properties":{"backupOwnerUserId":{"type":"string","format":"uuid"}},"required":["backupOwnerUserId"]},"UpdateAdminUserRequest":{"type":"object","properties":{"role":{"type":"string","enum":["EMPLOYEE","TEAM_LEAD","MANAGER","DIRECTOR","EXECUTIVE","ADMIN"]},"active":{"type":"boolean"}}},"AdminUserResponse":{"type":"object","properties":{"id":{"type":"string","format":"uuid"},"name":{"type":"string"},"email":{"type":"string"},"role":{"type":"string","enum":["EMPLOYEE","TEAM_LEAD","MANAGER","DIRECTOR","EXECUTIVE","ADMIN"]},"departmentId":{"type":"string","format":"uuid"},"active":{"type":"boolean"},"signInLinked":{"type":"boolean"},"mappedPrincipalCount":{"type":"integer","format":"int32"}}},"SessionResponse":{"type":"object","properties":{"authenticated":{"type":"boolean"},"name":{"type":"string"},"email":{"type":"string"},"userId":{"type":"string","format":"uuid"},"organizationId":{"type":"string","format":"uuid"},"departmentId":{"type":"string","format":"uuid"},"role":{"type":"string","enum":["EMPLOYEE","TEAM_LEAD","MANAGER","DIRECTOR","EXECUTIVE","ADMIN"]}}},"CsrfResponse":{"type":"object","properties":{"headerName":{"type":"string"},"parameterName":{"type":"string"},"token":{"type":"string"}}},"DepartmentResponse":{"type":"object","properties":{"id":{"type":"string","format":"uuid"},"organizationId":{"type":"string","format":"uuid"},"name":{"type":"string"}}},"OrganizationContextResponse":{"type":"object","properties":{"organizationId":{"type":"string","format":"uuid"},"departments":{"type":"array","items":{"$ref":"#/components/schemas/DepartmentResponse"}},"users":{"type":"array","items":{"$ref":"#/components/schemas/UserResponse"}}}},"UserResponse":{"type":"object","properties":{"id":{"type":"string","format":"uuid"},"organizationId":{"type":"string","format":"uuid"},"departmentId":{"type":"string","format":"uuid"},"name":{"type":"string"},"email":{"type":"string"},"role":{"type":"string","enum":["EMPLOYEE","TEAM_LEAD","MANAGER","DIRECTOR","EXECUTIVE","ADMIN"]}}},"MeResponse":{"type":"object","properties":{"authenticated":{"type":"boolean"},"subject":{"type":"string"},"email":{"type":"string"},"name":{"type":"string"},"authorizationProvider":{"type":"string"},"userId":{"type":"string","format":"uuid"},"organizationId":{"type":"string","format":"uuid"},"departmentId":{"type":"string","format":"uuid"},"role":{"type":"string","enum":["EMPLOYEE","TEAM_LEAD","MANAGER","DIRECTOR","EXECUTIVE","ADMIN"]}}},"KnowledgeEvidenceResponse":{"type":"object","properties":{"citationId":{"type":"string","format":"uuid"},"knowledgeAssetId":{"type":"string","format":"uuid"},"title":{"type":"string"},"content":{"type":"string"},"sourceUri":{"type":"string"},"startPage":{"type":"integer","format":"int32"},"endPage":{"type":"integer","format":"int32"},"heading":{"type":"string"},"relevanceScore":{"type":"number","format":"double"}}},"KnowledgeSearchResponse":{"type":"object","properties":{"requestId":{"type":"string"},"evidence":{"type":"array","items":{"$ref":"#/components/schemas/KnowledgeEvidenceResponse"}}}},"KnowledgeSpaceResponse":{"type":"object","properties":{"id":{"type":"string","format":"uuid"},"key":{"type":"string"},"name":{"type":"string"},"departmentId":{"type":"string","format":"uuid"}}},"AssetVersionResponse":{"type":"object","properties":{"id":{"type":"string","format":"uuid"},"assetId":{"type":"string","format":"uuid"},"versionNumber":{"type":"integer","format":"int32"},"promptTemplate":{"type":"string"},"workflowStepsJson":{"type":"string"},"inputSchemaJson":{"type":"string"},"outputSchemaJson":{"type":"string"},"exampleInput":{"type":"string"},"exampleOutput":{"type":"string"},"changeNote":{"type":"string"},"createdByUserId":{"type":"string","format":"uuid"},"createdAt":{"type":"string","format":"date-time"}}},"AdminSourceGroupMemberResponse":{"type":"object","properties":{"principalId":{"type":"string","format":"uuid"},"externalKey":{"type":"string"},"observedDisplayName":{"type":"string"},"observedEmail":{"type":"string"},"appUserId":{"type":"string","format":"uuid"},"appUserName":{"type":"string"}}},"AdminSourceGroupResponse":{"type":"object","properties":{"principalId":{"type":"string","format":"uuid"},"sourceSystem":{"type":"string"},"sourceConnectionKey":{"type":"string"},"externalKey":{"type":"string"},"observedDisplayName":{"type":"string"},"sourceAclSnapshotId":{"type":"string","format":"uuid"},"aclGeneration":{"type":"integer","format":"int64"},"sealedAt":{"type":"string","format":"date-time"},"members":{"type":"array","items":{"$ref":"#/components/schemas/AdminSourceGroupMemberResponse"}}}},"AdminConnectionActivityResponse":{"type":"object","properties":{"sourceSystem":{"type":"string"},"sourceConnectionKey":{"type":"string"},"objectsTotal":{"type":"integer","format":"int64"},"objectsActive":{"type":"integer","format":"int64"},"objectsArchived":{"type":"integer","format":"int64"},"lastObjectAt":{"type":"string","format":"date-time"},"lastCrawlAt":{"type":"string","format":"date-time"},"recentAttempts":{"type":"array","items":{"$ref":"#/components/schemas/AdminCrawlAttemptResponse"}}}},"AdminCrawlAttemptResponse":{"type":"object","properties":{"outcome":{"type":"string"},"objectsMaterialized":{"type":"integer","format":"int32"},"objectsRotated":{"type":"integer","format":"int32"},"objectsRematerialized":{"type":"integer","format":"int32"},"objectsRetired":{"type":"integer","format":"int32"},"objectsFailed":{"type":"integer","format":"int32"},"errorCode":{"type":"string"},"errorMessage":{"type":"string"},"attemptedAt":{"type":"string","format":"date-time"}}},"AdminConnectorSourceResponse":{"type":"object","properties":{"sourceSystem":{"type":"string"},"displayName":{"type":"string"}}}}}}